rgpio.py
rgpio-0.2.0.0.dist-info/LICENSE
rgpio-0.2.0.0.dist-info/METADATA
rgpio-0.2.0.0.dist-info/WHEEL
rgpio-0.2.0.0.dist-info/top_level.txt
rgpio-0.2.0.0.dist-info/RECORD
