Metadata-Version: 2.1
Name: rgpio
Version: 0.2.0.0
Summary: Linux SBC GPIO module
Home-page: http://abyz.me.uk/lg/py_rgpio.html
Author: joan
Author-email: joan@abyz.me.uk
Maintainer: joan
Maintainer-email: joan@abyz.me.uk
License: unlicense.org
Download-URL: http://abyz.me.uk/lg/lg.zip
Keywords: linux,sbc,gpio
Platform: UNKNOWN
Classifier: Programming Language :: Python :: 2
Classifier: Programming Language :: Python :: 3
License-File: LICENSE
